pymilvusdm/__init__.py
pymilvusdm/faiss_to_milvus.py
pymilvusdm/hdf5_to_milvus.py
pymilvusdm/main.py
pymilvusdm/milvus_to_hdf5.py
pymilvusdm/milvus_to_milvus.py
pymilvusdm/setting.py
pymilvusdm/core/__init__.py
pymilvusdm/core/data_to_milvus.py
pymilvusdm/core/milvus_client.py
pymilvusdm/core/read_data.py
pymilvusdm/core/read_faiss_data.py
pymilvusdm/core/read_milvus_data.py
pymilvusdm/core/read_milvus_meta.py
pymilvusdm/core/save_data.py
pymilvusdm/core/write_logs.py
pymilvusdm-2.0.dist-info/LICENSE
pymilvusdm-2.0.dist-info/METADATA
pymilvusdm-2.0.dist-info/WHEEL
pymilvusdm-2.0.dist-info/entry_points.txt
pymilvusdm-2.0.dist-info/top_level.txt
pymilvusdm-2.0.dist-info/RECORD
