Metadata-Version: 2.1
Name: pymilvusdm
Version: 2.0
Summary: Milvus data migration tool
Home-page: https://github.com/zilliz-bootcamp/milvus_data_migration
Author: ZILLIZ
License: Apache-2.0
Platform: UNKNOWN
Classifier: Programming Language :: Python :: 3.8
License-File: LICENSE
Requires-Dist: PyYAML
Requires-Dist: uuid
Requires-Dist: h5py
Requires-Dist: pymysql
Requires-Dist: tqdm
Requires-Dist: pymilvus-orm (==2.0.0rc1)
